{
"IDX_SPX": {
"p": 7479.17,
"d": 0.0,
"t": 7609.7798
},
"IDX_NDX": {
"p": 29178.555,
"d": 0.0,
"t": 30660.5996
},
"IDX_HSI": {
"p": 24199.46,
"d": 2.99,
"t": 27968.0898
},
"IDX_NIFTY": {
"p": 23882.05,
"d": -0.0,
"t": 26328.5508
},
"IDX_BTC": {
"p": 62180.96,
"d": -0.0,
"t": 124752.5312
},
"VRT": {
"p": 314.77,
"d": 3.01
},
"PRY": {
"p": 133.3,
"d": -0.37
},
"META": {
"p": 605.45,
"d": -1.65
},
"GOOGL": {
"p": 358.73,
"d": -2.26
},
"NFLX": {
"p": 76.215,
"d": 0.05
},
"AMZN": {
"p": 241.965,
"d": -1.63
},
"MSFT": {
"p": 383.955,
"d": -1.26
},
"NVDA": {
"p": 202.65,
"d": 2.9
},
"NBIS": {
"p": 210.499,
"d": 7.84
},
"MELI": {
"p": 1803.88,
"d": -0.54
},
"SE": {
"p": 105.19,
"d": 0.92
},
"UBER": {
"p": 73.24,
"d": -1.47
},
"AXON": {
"p": 607.51,
"d": -5.14
},
"IT": {
"p": 135.525,
"d": -3.75
},
"LULU": {
"p": 114.173,
"d": -0.78
},
"DECK": {
"p": 102.93,
"d": -2.97
},
"ONON": {
"p": 36.38,
"d": -0.66
},
"NKE": {
"p": 43.25,
"d": 0.09
},
"DIS": {
"p": 97.43,
"d": -0.05
},
"PYPL": {
"p": 44.31,
"d": -2.94
},
"FOUR": {
"p": 47.41,
"d": -7.33
},
"XYZ": {
"p": 76.13,
"d": -1.84
},
"BRK/B": {
"p": 497.865,
"d": -1.22
},
"LVMH": {
"p": 484.9,
"d": -2.2
},
"ADYEN": {
"p": 830.1,
"d": -3.26
},
"FFH": {
"p": 2392.36,
"d": -0.81
},
"6501.T": {
"p": 4778.0,
"d": -3.32
},
"XEON": {
"p": 149.569,
"d": -0.01
},
"ISAC": {
"p": 104.89,
"d": -0.66
},
"XDWH": {
"p": 53.52,
"d": -0.69
},
"URNU": {
"p": 21.565,
"d": -1.8
},
"KWBE": {
"p": 12.294,
"d": 3.76
},
"FLXI": {
"p": 35.72,
"d": -1.53
},
"ABT": {
"p": 95.41,
"d": -0.45
},
"CMG": {
"p": 33.655,
"d": -2.02
},
"ISRG": {
"p": 418.94,
"d": -1.96
},
"STZ": {
"p": 130.92,
"d": -0.64
},
"TMDX": {
"p": 69.955,
"d": -1.63
},
"NU": {
"p": 13.335,
"d": -2.02
},
"PDD": {
"p": 84.86,
"d": 2.82
},
"LEU": {
"p": 165.5,
"d": -0.08
},
"ALC": {
"p": 66.935,
"d": 0.1
},
"ABF": {
"p": 1942.0,
"d": -1.42
},
"HEIA": {
"p": 75.64,
"d": -1.54
},
"NMAN": {
"p": 123.4,
"d": -4.04
},
"HESAY": {
"p": 180.21,
"d": -3.18
},
"PDRDF": {
"p": 74.0,
"d": -2.27
},
"ESIS": {
"p": 6.11,
"d": -1.36
},
"DAPP": {
"p": 11.092,
"d": -1.82
},
"CI2": {
"p": 35.72,
"d": -1.53
},
"CPH": {
"p": 16.88,
"d": -2.6
},
"CSBGE7": {
"p": 133.56,
"d": -0.59
},
"LEMA": {
"p": 73.4,
"d": -0.15
},
"MMM": {
"p": 155.188,
"d": -1.79
},
"ABBV": {
"p": 254.19,
"d": -0.18
},
"ACN": {
"p": 138.37,
"d": -2.65
},
"ADBE": {
"p": 221.095,
"d": -0.2
},
"AD": {
"p": 35.0,
"d": 0.34
},
"ABNB": {
"p": 142.775,
"d": -4.05
},
"BABA": {
"p": 109.575,
"d": 11.65
},
"AMD": {
"p": 513.195,
"d": -0.56
},
"AAPL": {
"p": 314.2,
"d": 1.14
},
"APP": {
"p": 523.635,
"d": -0.82
},
"ADM": {
"p": 80.39,
"d": 2.8
},
"ARM": {
"p": 295.675,
"d": -1.58
},
"ASML": {
"p": 1777.235,
"d": 1.71
},
"B": {
"p": 35.5,
"d": -3.69
},
"BLCO": {
"p": 16.615,
"d": -2.84
},
"BHP": {
"p": 78.25,
"d": -2.47
},
"BA": {
"p": 224.17,
"d": -3.24
},
"BKNG": {
"p": 174.46,
"d": -4.12
},
"AVGO": {
"p": 389.46,
"d": 5.04
},
"BAM": {
"p": 45.435,
"d": -2.44
},
"BN": {
"p": 42.925,
"d": -1.98
},
"BC": {
"p": 75.795,
"d": -1.98
},
"BZZUY": {
"p": 25.55,
"d": -0.39
},
"BYDDY": {
"p": 10.8,
"d": 2.18
},
"CPRI": {
"p": 17.95,
"d": -7.57
},
"CAVA": {
"p": 67.86,
"d": -2.7
},
"CELH": {
"p": 30.438,
"d": -3.98
},
"CLSK": {
"p": 12.168,
"d": -2.5
},
"NET": {
"p": 268.3,
"d": -0.2
},
"KO": {
"p": 83.985,
"d": -0.08
},
"CL": {
"p": 93.39,
"d": -1.73
},
"CFRUY": {
"p": 22.42,
"d": -1.88
},
"CPRT": {
"p": 28.61,
"d": -2.25
},
"CRWV": {
"p": 87.18,
"d": 4.37
},
"CPNG": {
"p": 18.925,
"d": 2.13
},
"CROX": {
"p": 122.01,
"d": -2.04
},
"CRWD": {
"p": 189.3,
"d": -2.73
},
"DJCO": {
"p": 573.13,
"d": 1.53
},
"QTUM": {
"p": 152.23,
"d": 0.52
},
"DEO": {
"p": 81.26,
"d": -1.91
},
"DLO": {
"p": 14.52,
"d": -2.42
},
"DUOL": {
"p": 126.97,
"d": -3.77
},
"EDEN": {
"p": 112.98,
"d": -1.54
},
"ERFSF": {
"p": 78.75,
"d": 1.56
},
"FMX": {
"p": 127.64,
"d": -1.44
},
"RACE": {
"p": 375.15,
"d": -3.06
},
"FBK": {
"p": 56.03,
"d": -1.6
},
"FVRR": {
"p": 10.76,
"d": -4.1
},
"FMC": {
"p": 10.98,
"d": -5.26
},
"FTNT": {
"p": 156.17,
"d": -1.58
},
"GRAB": {
"p": 3.84,
"d": -2.29
},
"HIMS": {
"p": 35.86,
"d": -0.86
},
"IDEXY": {
"p": 15.55,
"d": -3.48
},
"INFY": {
"p": 11.055,
"d": -1.91
},
"INTC": {
"p": 107.637,
"d": -2.49
},
"IWB": {
"p": 407.93,
"d": -0.43
},
"JDSPY": {
"p": 1.05,
"d": -0.94
},
"JD": {
"p": 27.665,
"d": 4.44
},
"JEDI": {
"p": 26.33,
"d": -1.02
},
"JNJ": {
"p": 266.09,
"d": -0.43
},
"JMIA": {
"p": 6.819,
"d": -1.74
},
"KWEB": {
"p": 26.465,
"d": 3.74
},
"LMND": {
"p": 70.544,
"d": -9.08
},
"LVMHF": {
"p": 558.0,
"d": -1.1
},
"MOH": {
"p": 232.1,
"d": -0.34
},
"LYFT": {
"p": 14.995,
"d": -2.88
},
"AMKBY": {
"p": 12.53,
"d": 3.04
},
"MKL": {
"p": 1958.985,
"d": -0.53
},
"MAR": {
"p": 372.7,
"d": -2.11
},
"MASI": {
"p": 179.95,
"d": 0.0
},
"MCD": {
"p": 278.26,
"d": -1.4
},
"Meli": {
"p": 1803.46,
"d": -0.56
},
"MNDY": {
"p": 81.935,
"d": -2.57
},
"NDX": {
"p": 17421.0,
"d": 0.1
},
"NEM": {
"p": 92.95,
"d": -2.22
},
"NEXI": {
"p": 0.0001,
"d": 0.0
},
"NTDOY": {
"p": 10.84,
"d": -2.08
},
"NVO": {
"p": 49.305,
"d": -0.67
},
"NTNX": {
"p": 53.395,
"d": -0.68
},
"NVR": {
"p": 6450.0,
"d": -3.64
},
"OKLO": {
"p": 47.19,
"d": -1.48
},
"OKTA": {
"p": 145.185,
"d": -2.21
},
"ORCL": {
"p": 139.105,
"d": -1.76
},
"OSCR": {
"p": 30.7,
"d": -1.35
},
"PLTR": {
"p": 130.25,
"d": -3.07
},
"PEP": {
"p": 144.11,
"d": -0.6
},
"PSH": {
"p": 49.875,
"d": -0.14
},
"PFE": {
"p": 24.21,
"d": 0.58
},
"PG": {
"p": 148.98,
"d": -2.47
},
"PUBM": {
"p": 12.97,
"d": -2.63
},
"RL": {
"p": 385.975,
"d": -2.36
},
"RELY": {
"p": 23.185,
"d": -3.92
},
"REY.MI": {
"p": 94.85,
"d": -2.01
},
"RIO": {
"p": 88.17,
"d": -3.38
},
"RKLB": {
"p": 82.314,
"d": -1.31
},
"RBSFY": {
"p": 7.46,
"d": 7.59
},
"RYAAY": {
"p": 65.625,
"d": -1.09
},
"VOO": {
"p": 684.27,
"d": -0.41
},
"CRM": {
"p": 166.6,
"d": -1.72
},
"IOT": {
"p": 35.807,
"d": -1.47
},
"SMTI": {
"p": 24.18,
"d": -2.46
},
"SAP": {
"p": 157.85,
"d": -3.02
},
"SES": {
"p": 0.8004,
"d": -0.99
},
"SMH": {
"p": 591.045,
"d": 1.65
},
"NOW": {
"p": 107.326,
"d": -3.07
},
"SHOP": {
"p": 117.415,
"d": -3.66
},
"SNOW": {
"p": 259.62,
"d": -1.19
},
"SBUX": {
"p": 103.665,
"d": 0.05
},
"STNE": {
"p": 10.56,
"d": -1.12
},
"SG": {
"p": 7.74,
"d": 0.0
},
"TROW": {
"p": 117.825,
"d": -1.94
},
"TSM": {
"p": 436.535,
"d": 0.92
},
"TPR": {
"p": 140.75,
"d": -3.79
},
"TGT": {
"p": 133.175,
"d": 4.41
},
"TDOC": {
"p": 9.115,
"d": -4.25
},
"TCEHY": {
"p": 60.63,
"d": 2.9
},
"TSLA": {
"p": 391.25,
"d": -2.89
},
"HEAL": {
"p": 28.7,
"d": -1.61
},
"TTD": {
"p": 18.925,
"d": -1.33
},
"PATH": {
"p": 11.42,
"d": -1.97
},
"ULTA": {
"p": 457.56,
"d": 0.83
},
"UA": {
"p": 6.405,
"d": -2.51
},
"UNH": {
"p": 424.775,
"d": -0.8
},
"GDX": {
"p": 73.295,
"d": -3.25
},
"QNTM": {
"p": 3.17,
"d": -4.52
},
"VEEV": {
"p": 189.4,
"d": -1.51
},
"V": {
"p": 348.53,
"d": -1.04
},
"VST": {
"p": 152.795,
"d": -1.88
},
"WBD": {
"p": 26.195,
"d": 0.29
},
"WM": {
"p": 235.48,
"d": -0.73
},
"XOVR": {
"p": 20.61,
"d": -1.01
},
"ZM": {
"p": 87.32,
"d": 1.91
},
"IFX": {
"p": 70.3,
"d": -0.75
},
"SAN": {
"p": 75.37,
"d": -0.54
},
"ALV": {
"p": 418.5,
"d": -1.02
},
"HDB": {
"p": 26.255,
"d": -3.23
},
"SU": {
"p": 263.8,
"d": -1.57
},
"RHM": {
"p": 1058.8,
"d": -4.75
},
"AEM": {
"p": 144.446,
"d": -3.91
},
"8058.T": {
"p": 4464.0,
"d": -0.8
},
"AZN": {
"p": 189.835,
"d": -1.7
},
"CCJ": {
"p": 94.115,
"d": -0.59
},
"AXA": {
"p": 44.01,
"d": -0.65
},
"TLX": {
"p": 109.5,
"d": -5.44
},
"MRK.DE": {
"p": 139.15,
"d": -1.83
},
"RDY": {
"p": 14.449,
"d": -1.24
},
"BAP": {
"p": 381.03,
"d": -1.41
},
"EURUSD": {
"p": 1.1427,
"d": 0.16
},
"EURJPY": {
"p": 185.622,
"d": 0.41
},
"EURCAD": {
"p": 1.6186,
"d": -0.04
},
"EURGBP": {
"p": 0.8525,
"d": -0.19
},
"EURCHF": {
"p": 0.923,
"d": 0.15
},
"EURSEK": {
"p": 11.0717,
"d": 0.15
},
"APLD": {
"p": 30.58,
"d": -0.42
},
"IREN": {
"p": 41.12,
"d": 3.28
},
"MRVL": {
"p": 232.4,
"d": 0.74
},
"MU": {
"p": 937.355,
"d": -0.11
},
"SOFI": {
"p": 17.475,
"d": -1.55
},
"STM": {
"p": 68.24,
"d": 1.43
},
"REC": {
"p": 51.6,
"d": 0.39
},
"MUV2": {
"p": 505.8,
"d": -0.43
},
"IBN": {
"p": 28.967,
"d": -2.44
},
"IBE": {
"p": 21.02,
"d": 0.0
},
"GEV": {
"p": 1088.0,
"d": 1.01
},
"_updated": "2026-07-08 18:31:44 UTC"
}