{
"IDX_SPX": {
"p": 7534.34,
"d": 0.0,
"t": 7609.7798
},
"IDX_NDX": {
"p": 30129.3,
"d": -0.0,
"t": 30660.5996
},
"IDX_HSI": {
"p": 24493.95,
"d": -0.91,
"t": 27968.0898
},
"IDX_NIFTY": {
"p": 23989.15,
"d": -0.0,
"t": 26328.5508
},
"IDX_BTC": {
"p": 65680.73,
"d": 0.0,
"t": 124752.5312
},
"VRT": {
"p": 307.815,
"d": -1.32
},
"PRY": {
"p": 146.35,
"d": 0.55
},
"META": {
"p": 596.835,
"d": 0.57
},
"GOOGL": {
"p": 369.871,
"d": 0.14
},
"NFLX": {
"p": 79.035,
"d": -3.23
},
"AMZN": {
"p": 246.13,
"d": 0.01
},
"MSFT": {
"p": 392.14,
"d": -1.91
},
"NVDA": {
"p": 208.765,
"d": -1.73
},
"NBIS": {
"p": 269.06,
"d": 3.46
},
"MELI": {
"p": 1670.0,
"d": 1.44
},
"SE": {
"p": 87.31,
"d": 0.75
},
"UBER": {
"p": 74.27,
"d": 1.95
},
"AXON": {
"p": 435.1,
"d": -1.83
},
"IT": {
"p": 142.405,
"d": -0.26
},
"LULU": {
"p": 117.16,
"d": 0.82
},
"DECK": {
"p": 112.5,
"d": 0.0
},
"ONON": {
"p": 38.61,
"d": -0.21
},
"NKE": {
"p": 45.555,
"d": 0.79
},
"DIS": {
"p": 100.86,
"d": -0.82
},
"PYPL": {
"p": 43.514,
"d": 2.41
},
"FOUR": {
"p": 41.345,
"d": 3.52
},
"XYZ": {
"p": 75.84,
"d": 2.0
},
"BRK/B": {
"p": 497.25,
"d": 0.35
},
"LVMH": {
"p": 520.3,
"d": 1.5
},
"ADYEN": {
"p": 890.3,
"d": 3.66
},
"FFH": {
"p": 2280.08,
"d": 0.51
},
"HTHIY": {
"p": 4747.0,
"d": 0.21
},
"XEON": {
"p": 149.369,
"d": 0.0
},
"ISAC": {
"p": 122.06,
"d": -0.14
},
"XDWH": {
"p": 49.325,
"d": -0.31
},
"URNU": {
"p": 29.555,
"d": 0.14
},
"FLXI": {
"p": 35.73,
"d": 0.29
},
"ABT": {
"p": 89.855,
"d": 1.34
},
"CMG": {
"p": 33.1,
"d": 1.13
},
"ISRG": {
"p": 418.65,
"d": 0.5
},
"STZ": {
"p": 145.495,
"d": -1.78
},
"TMDX": {
"p": 75.55,
"d": 0.09
},
"NU": {
"p": 12.705,
"d": 2.21
},
"PDD": {
"p": 80.93,
"d": -3.14
},
"LEU": {
"p": 168.24,
"d": -4.76
},
"ALC": {
"p": 66.35,
"d": 0.09
},
"ABF": {
"p": 1894.0,
"d": -1.69
},
"HEIA": {
"p": 70.46,
"d": 0.14
},
"NMAN": {
"p": 126.2,
"d": -1.25
},
"HESAY": {
"p": 203.31,
"d": 2.19
},
"PDRDF": {
"p": 71.88,
"d": 1.01
},
"ESIS": {
"p": 5.868,
"d": -0.17
},
"DAPP": {
"p": 15.706,
"d": 0.45
},
"CI2": {
"p": 35.73,
"d": 0.29
},
"CPH": {
"p": 16.1,
"d": -0.62
},
"CSBGE7": {
"p": 134.5,
"d": 0.09
},
"LEMA": {
"p": 76.48,
"d": -1.01
},
"MMM": {
"p": 162.35,
"d": 2.6
},
"ABBV": {
"p": 221.96,
"d": 0.17
},
"ACN": {
"p": 166.33,
"d": 0.59
},
"ADBE": {
"p": 208.22,
"d": 0.9
},
"AD": {
"p": 39.63,
"d": -0.38
},
"ABNB": {
"p": 141.04,
"d": 1.5
},
"BABA": {
"p": 109.67,
"d": -2.56
},
"AMD": {
"p": 520.43,
"d": -4.9
},
"AAPL": {
"p": 299.46,
"d": 1.03
},
"APP": {
"p": 497.185,
"d": -4.55
},
"ADM": {
"p": 77.955,
"d": -1.66
},
"ARM": {
"p": 405.15,
"d": -1.79
},
"ASML": {
"p": 1833.64,
"d": -3.12
},
"B": {
"p": 42.84,
"d": 2.41
},
"BLCO": {
"p": 15.14,
"d": 0.93
},
"BHP": {
"p": 92.96,
"d": 0.9
},
"BA": {
"p": 228.785,
"d": -0.07
},
"BKNG": {
"p": 175.83,
"d": 0.68
},
"AVGO": {
"p": 378.93,
"d": -3.81
},
"BAM": {
"p": 48.92,
"d": 1.51
},
"BN": {
"p": 45.94,
"d": 0.57
},
"BC": {
"p": 82.53,
"d": 0.49
},
"BZZUY": {
"p": 26.5,
"d": -2.47
},
"BYDDY": {
"p": 10.58,
"d": -3.29
},
"CPRI": {
"p": 21.2,
"d": 0.66
},
"CAVA": {
"p": 88.835,
"d": -0.77
},
"CELH": {
"p": 28.665,
"d": -0.26
},
"CLSK": {
"p": 17.865,
"d": 4.23
},
"NET": {
"p": 232.535,
"d": -1.35
},
"KO": {
"p": 80.355,
"d": -0.69
},
"CL": {
"p": 91.335,
"d": 0.83
},
"CFRUY": {
"p": 23.04,
"d": 1.9
},
"CPRT": {
"p": 30.48,
"d": 0.59
},
"CRWV": {
"p": 116.97,
"d": 9.61
},
"CPNG": {
"p": 17.945,
"d": 4.76
},
"CROX": {
"p": 128.22,
"d": 1.54
},
"CRWD": {
"p": 682.47,
"d": -1.51
},
"DJCO": {
"p": 554.05,
"d": -0.41
},
"QTUM": {
"p": 164.175,
"d": -2.31
},
"DEO": {
"p": 80.77,
"d": 0.6
},
"DLO": {
"p": 12.695,
"d": 0.28
},
"DUOL": {
"p": 126.27,
"d": -0.62
},
"EDEN": {
"p": 107.735,
"d": -0.87
},
"ERFSF": {
"p": 72.76,
"d": -5.17
},
"FMX": {
"p": 127.34,
"d": 0.79
},
"RACE": {
"p": 368.53,
"d": -0.14
},
"FBK": {
"p": 54.125,
"d": 0.64
},
"FVRR": {
"p": 9.875,
"d": -0.95
},
"FMC": {
"p": 11.645,
"d": 1.17
},
"FTNT": {
"p": 145.57,
"d": -2.62
},
"GRAB": {
"p": 3.535,
"d": 2.17
},
"HIMS": {
"p": 31.87,
"d": 5.63
},
"IDEXY": {
"p": 16.24,
"d": -0.92
},
"INFY": {
"p": 12.005,
"d": 3.49
},
"INTC": {
"p": 119.952,
"d": -6.18
},
"IWB": {
"p": 410.55,
"d": -0.29
},
"JDSPY": {
"p": 1.13,
"d": 0.89
},
"JD": {
"p": 28.285,
"d": -1.38
},
"JEDI": {
"p": 30.865,
"d": -3.34
},
"JNJ": {
"p": 235.135,
"d": -0.22
},
"JMIA": {
"p": 7.275,
"d": -1.69
},
"KWEB": {
"p": 25.91,
"d": -2.67
},
"LMND": {
"p": 61.025,
"d": 0.45
},
"LVMHF": {
"p": 605.02,
"d": 1.68
},
"MOH": {
"p": 203.58,
"d": 0.85
},
"LYFT": {
"p": 14.43,
"d": 1.33
},
"AMKBY": {
"p": 12.34,
"d": -3.14
},
"MKL": {
"p": 1876.895,
"d": 1.23
},
"MAR": {
"p": 398.675,
"d": -0.49
},
"MASI": {
"p": 179.95,
"d": 0.0
},
"MCD": {
"p": 287.495,
"d": 0.48
},
"Meli": {
"p": 1668.81,
"d": 1.36
},
"MNDY": {
"p": 75.007,
"d": -2.92
},
"NDX": {
"p": 17421.0,
"d": 0.1
},
"NEM": {
"p": 108.51,
"d": 2.56
},
"NEXI": {
"p": 0.0001,
"d": 0.0
},
"NTDOY": {
"p": 11.19,
"d": 1.45
},
"NVO": {
"p": 43.77,
"d": -0.34
},
"NTNX": {
"p": 47.975,
"d": -2.88
},
"NVR": {
"p": 6476.005,
"d": 2.23
},
"OKLO": {
"p": 58.665,
"d": -3.42
},
"OKTA": {
"p": 116.68,
"d": -1.22
},
"ORCL": {
"p": 189.12,
"d": -1.83
},
"OSCR": {
"p": 28.57,
"d": -1.96
},
"PLTR": {
"p": 130.98,
"d": -2.77
},
"PEP": {
"p": 145.965,
"d": -0.19
},
"PSH": {
"p": 50.06,
"d": 0.04
},
"PFE": {
"p": 26.094,
"d": 0.36
},
"PG": {
"p": 152.305,
"d": 1.23
},
"PUBM": {
"p": 11.55,
"d": 0.7
},
"RL": {
"p": 413.785,
"d": 0.35
},
"RELY": {
"p": 20.085,
"d": 2.32
},
"REY.MI": {
"p": 100.8,
"d": 1.2
},
"RIO": {
"p": 106.247,
"d": 0.34
},
"RKLB": {
"p": 105.99,
"d": -2.98
},
"RBSFY": {
"p": 8.7,
"d": 0.0
},
"RYAAY": {
"p": 62.51,
"d": 1.03
},
"VOO": {
"p": 692.025,
"d": -0.26
},
"CRM": {
"p": 160.8,
"d": -2.28
},
"IOT": {
"p": 32.49,
"d": -3.13
},
"SMTI": {
"p": 22.28,
"d": 1.8
},
"SAP": {
"p": 164.8,
"d": 0.29
},
"SES": {
"p": 1.085,
"d": -3.13
},
"SMH": {
"p": 629.72,
"d": -2.69
},
"NOW": {
"p": 101.59,
"d": -2.46
},
"SHOP": {
"p": 112.92,
"d": 0.38
},
"SNOW": {
"p": 238.55,
"d": -0.93
},
"SBUX": {
"p": 101.385,
"d": -0.2
},
"STNE": {
"p": 10.95,
"d": -0.36
},
"SG": {
"p": 9.21,
"d": 3.95
},
"TROW": {
"p": 109.31,
"d": 0.64
},
"TSM": {
"p": 432.187,
"d": -2.09
},
"TPR": {
"p": 151.185,
"d": 0.13
},
"TGT": {
"p": 133.89,
"d": 0.54
},
"TDOC": {
"p": 7.465,
"d": 0.07
},
"TCEHY": {
"p": 56.78,
"d": -3.44
},
"TSLA": {
"p": 405.12,
"d": -1.47
},
"HEAL": {
"p": 26.19,
"d": 0.15
},
"TTD": {
"p": 19.17,
"d": -0.52
},
"PATH": {
"p": 10.52,
"d": -2.5
},
"ULTA": {
"p": 467.62,
"d": -0.85
},
"UA": {
"p": 5.845,
"d": -0.09
},
"UNH": {
"p": 411.22,
"d": 0.04
},
"GDX": {
"p": 87.04,
"d": 2.08
},
"QNTM": {
"p": 3.6,
"d": -2.7
},
"VEEV": {
"p": 160.83,
"d": -0.83
},
"V": {
"p": 331.8,
"d": 2.46
},
"VST": {
"p": 161.04,
"d": 4.9
},
"WBD": {
"p": 26.655,
"d": -0.65
},
"WM": {
"p": 217.0,
"d": 0.03
},
"XOVR": {
"p": 21.31,
"d": 1.86
},
"ZM": {
"p": 91.88,
"d": -2.51
},
"IFX": {
"p": 79.28,
"d": -1.82
},
"SAN": {
"p": 75.66,
"d": 0.16
},
"ALV": {
"p": 399.0,
"d": 1.09
},
"HDB": {
"p": 25.235,
"d": 2.0
},
"SU": {
"p": 276.95,
"d": 2.52
},
"RHM": {
"p": 1145.6,
"d": -0.4
},
"AEM": {
"p": 176.07,
"d": 2.49
},
"8058.T": {
"p": 4595.0,
"d": -2.81
},
"AZN": {
"p": 178.63,
"d": 0.77
},
"CCJ": {
"p": 107.83,
"d": 0.76
},
"AXA": {
"p": 42.35,
"d": 1.12
},
"TLX": {
"p": 104.0,
"d": 1.56
},
"MRK.DE": {
"p": 132.05,
"d": -0.49
},
"RDY": {
"p": 13.355,
"d": 0.19
},
"BAP": {
"p": 365.45,
"d": 0.86
},
"EURUSD": {
"p": 1.1617,
"d": 0.2
},
"EURJPY": {
"p": 186.261,
"d": 0.25
},
"EURCAD": {
"p": 1.624,
"d": 0.21
},
"EURGBP": {
"p": 0.8648,
"d": 0.07
},
"EURCHF": {
"p": 0.9205,
"d": -0.02
},
"EURSEK": {
"p": 10.8646,
"d": -0.31
},
"APLD": {
"p": 47.085,
"d": 1.32
},
"IREN": {
"p": 60.275,
"d": -0.94
},
"MRVL": {
"p": 292.95,
"d": -5.16
},
"MU": {
"p": 1047.041,
"d": -3.76
},
"SOFI": {
"p": 17.925,
"d": 4.64
},
"STM": {
"p": 76.04,
"d": -3.69
},
"REC": {
"p": 50.6,
"d": -0.1
},
"MUV2": {
"p": 468.8,
"d": 1.32
},
"IBN": {
"p": 28.225,
"d": 1.49
},
"IBE": {
"p": 20.58,
"d": 0.44
},
"GEV": {
"p": 1003.38,
"d": 2.54
},
"_updated": "2026-06-16 17:00:57 UTC"
}