{
"IDX_SPX": {
"p": 7521.21,
"d": -0.72,
"t": 7609.7798
},
"IDX_NDX": {
"p": 29282.0,
"d": -1.82,
"t": 30660.5996
},
"IDX_HSI": {
"p": 24213.72,
"d": 0.16,
"t": 27968.0898
},
"IDX_NIFTY": {
"p": 24211.0,
"d": 0.02,
"t": 26328.5508
},
"IDX_BTC": {
"p": 61939.16,
"d": -0.0,
"t": 124752.5312
},
"VRT": {
"p": 304.81,
"d": -4.41
},
"PRY": {
"p": 133.35,
"d": -1.26
},
"META": {
"p": 660.81,
"d": -1.26
},
"GOOGL": {
"p": 354.855,
"d": -0.65
},
"NFLX": {
"p": 74.28,
"d": 1.24
},
"AMZN": {
"p": 248.96,
"d": 1.48
},
"MSFT": {
"p": 393.186,
"d": 2.1
},
"NVDA": {
"p": 203.71,
"d": -3.44
},
"NBIS": {
"p": 206.995,
"d": -5.76
},
"MELI": {
"p": 1873.53,
"d": 1.15
},
"SE": {
"p": 111.99,
"d": 0.76
},
"UBER": {
"p": 74.59,
"d": 0.07
},
"AXON": {
"p": 553.36,
"d": -2.2
},
"IT": {
"p": 140.29,
"d": 5.29
},
"LULU": {
"p": 121.06,
"d": 1.51
},
"DECK": {
"p": 107.91,
"d": 1.81
},
"ONON": {
"p": 37.95,
"d": -1.53
},
"NKE": {
"p": 44.26,
"d": -0.25
},
"DIS": {
"p": 96.145,
"d": 0.55
},
"PYPL": {
"p": 47.75,
"d": 3.09
},
"FOUR": {
"p": 50.19,
"d": -1.22
},
"XYZ": {
"p": 78.155,
"d": 1.11
},
"BRK/B": {
"p": 497.59,
"d": 0.79
},
"LVMH": {
"p": 491.5,
"d": 0.33
},
"ADYEN": {
"p": 843.7,
"d": -0.34
},
"FFH": {
"p": 2354.23,
"d": 0.05
},
"6501.T": {
"p": 4716.0,
"d": 0.34
},
"XEON": {
"p": 149.618,
"d": 0.01
},
"ISAC": {
"p": 106.28,
"d": -0.16
},
"XDWH": {
"p": 52.73,
"d": 0.15
},
"URNU": {
"p": 22.075,
"d": -3.14
},
"KWBE": {
"p": 12.212,
"d": -0.63
},
"FLXI": {
"p": 36.11,
"d": -0.51
},
"ABT": {
"p": 92.695,
"d": -1.31
},
"CMG": {
"p": 36.99,
"d": 4.94
},
"ISRG": {
"p": 409.525,
"d": 0.67
},
"STZ": {
"p": 134.855,
"d": 0.59
},
"TMDX": {
"p": 75.78,
"d": 6.39
},
"NU": {
"p": 13.711,
"d": -0.36
},
"PDD": {
"p": 84.76,
"d": -0.43
},
"LEU": {
"p": 160.21,
"d": -6.34
},
"ALC": {
"p": 68.905,
"d": 1.61
},
"ABF": {
"p": 2004.0,
"d": 0.8
},
"HEIA": {
"p": 75.8,
"d": 0.0
},
"NMAN": {
"p": 127.6,
"d": 0.63
},
"HESAY": {
"p": 187.3,
"d": 0.05
},
"PDRDF": {
"p": 74.0,
"d": 0.0
},
"ESIS": {
"p": 6.08,
"d": 0.18
},
"DAPP": {
"p": 11.196,
"d": -2.96
},
"CI2": {
"p": 36.11,
"d": -0.51
},
"CPH": {
"p": 16.79,
"d": -1.98
},
"CSBGE7": {
"p": 133.71,
"d": -0.26
},
"LEMA": {
"p": 73.5,
"d": -2.49
},
"MMM": {
"p": 157.515,
"d": -0.0
},
"ABBV": {
"p": 247.34,
"d": -0.3
},
"ACN": {
"p": 138.55,
"d": 2.46
},
"ADBE": {
"p": 230.57,
"d": 3.1
},
"AD": {
"p": 34.61,
"d": -0.12
},
"ABNB": {
"p": 145.22,
"d": -2.29
},
"BABA": {
"p": 112.755,
"d": 0.38
},
"AMD": {
"p": 535.61,
"d": -3.99
},
"AAPL": {
"p": 317.19,
"d": 0.59
},
"APP": {
"p": 450.81,
"d": -11.08
},
"ADM": {
"p": 82.29,
"d": 2.34
},
"ARM": {
"p": 297.325,
"d": -8.06
},
"ASML": {
"p": 1728.25,
"d": -3.84
},
"B": {
"p": 35.713,
"d": -2.64
},
"BLCO": {
"p": 16.14,
"d": -0.55
},
"BHP": {
"p": 81.13,
"d": -0.67
},
"BA": {
"p": 215.28,
"d": -3.15
},
"BKNG": {
"p": 175.28,
"d": -1.74
},
"AVGO": {
"p": 385.33,
"d": -3.66
},
"BAM": {
"p": 46.342,
"d": -0.81
},
"BN": {
"p": 43.245,
"d": -1.11
},
"BC": {
"p": 77.03,
"d": -1.12
},
"BZZUY": {
"p": 25.95,
"d": 4.81
},
"BYDDY": {
"p": 10.57,
"d": -2.22
},
"CPRI": {
"p": 17.748,
"d": -1.62
},
"CAVA": {
"p": 72.04,
"d": -0.19
},
"CELH": {
"p": 29.805,
"d": -2.6
},
"CLSK": {
"p": 12.165,
"d": -5.33
},
"NET": {
"p": 268.66,
"d": 0.1
},
"KO": {
"p": 84.43,
"d": 1.13
},
"CL": {
"p": 92.975,
"d": 0.8
},
"CFRUY": {
"p": 22.52,
"d": -0.4
},
"CPRT": {
"p": 27.5,
"d": -0.05
},
"CRWV": {
"p": 83.145,
"d": -6.45
},
"CPNG": {
"p": 18.255,
"d": -2.9
},
"CROX": {
"p": 131.34,
"d": -1.08
},
"CRWD": {
"p": 188.44,
"d": 0.67
},
"DJCO": {
"p": 579.98,
"d": 0.69
},
"QTUM": {
"p": 149.055,
"d": -3.5
},
"DEO": {
"p": 82.675,
"d": 0.79
},
"DLO": {
"p": 14.875,
"d": -2.07
},
"DUOL": {
"p": 131.185,
"d": 5.15
},
"EDEN": {
"p": 113.795,
"d": -0.38
},
"ERFSF": {
"p": 78.75,
"d": -1.84
},
"FMX": {
"p": 128.37,
"d": 0.56
},
"RACE": {
"p": 373.336,
"d": -0.88
},
"FBK": {
"p": 56.71,
"d": 0.05
},
"FVRR": {
"p": 11.29,
"d": 2.26
},
"FMC": {
"p": 11.005,
"d": 0.87
},
"FTNT": {
"p": 160.99,
"d": 2.21
},
"GRAB": {
"p": 3.974,
"d": 1.12
},
"HIMS": {
"p": 34.19,
"d": -0.55
},
"IDEXY": {
"p": 15.53,
"d": -0.89
},
"INFY": {
"p": 11.46,
"d": 4.75
},
"INTC": {
"p": 102.29,
"d": -6.87
},
"IWB": {
"p": 409.96,
"d": -0.76
},
"JDSPY": {
"p": 1.12,
"d": 8.74
},
"JD": {
"p": 28.91,
"d": 2.52
},
"JEDI": {
"p": 24.5,
"d": -4.15
},
"JNJ": {
"p": 258.08,
"d": 0.43
},
"JMIA": {
"p": 6.73,
"d": -3.99
},
"KWEB": {
"p": 26.19,
"d": -0.72
},
"LMND": {
"p": 70.27,
"d": -0.34
},
"LVMHF": {
"p": 558.5,
"d": 0.09
},
"MOH": {
"p": 239.225,
"d": 2.54
},
"LYFT": {
"p": 15.65,
"d": 0.26
},
"AMKBY": {
"p": 12.65,
"d": 5.5
},
"MKL": {
"p": 1961.92,
"d": 0.62
},
"MAR": {
"p": 366.29,
"d": -2.61
},
"MASI": {
"p": 179.95,
"d": 0.0
},
"MCD": {
"p": 272.695,
"d": -0.69
},
"Meli": {
"p": 1873.0,
"d": 1.12
},
"MNDY": {
"p": 86.58,
"d": 4.98
},
"NDX": {
"p": 17421.0,
"d": 0.1
},
"NEM": {
"p": 92.89,
"d": -2.52
},
"NEXI": {
"p": 0.0001,
"d": 0.0
},
"NTDOY": {
"p": 10.88,
"d": -0.82
},
"NVO": {
"p": 49.196,
"d": -0.57
},
"NTNX": {
"p": 55.07,
"d": 0.51
},
"NVR": {
"p": 6455.788,
"d": -0.36
},
"OKLO": {
"p": 45.51,
"d": -6.84
},
"OKTA": {
"p": 138.97,
"d": 0.25
},
"ORCL": {
"p": 133.11,
"d": -5.35
},
"OSCR": {
"p": 31.595,
"d": 3.45
},
"PLTR": {
"p": 129.565,
"d": 2.19
},
"PEP": {
"p": 138.67,
"d": 0.94
},
"PSH": {
"p": 49.85,
"d": -0.14
},
"PFE": {
"p": 24.439,
"d": 1.11
},
"PG": {
"p": 148.11,
"d": 0.73
},
"PUBM": {
"p": 13.55,
"d": 0.0
},
"RL": {
"p": 376.57,
"d": -4.64
},
"RELY": {
"p": 24.03,
"d": 1.09
},
"REY.MI": {
"p": 96.75,
"d": 1.36
},
"RIO": {
"p": 89.49,
"d": -1.16
},
"RKLB": {
"p": 76.055,
"d": -6.15
},
"RBSFY": {
"p": 7.46,
"d": 3.24
},
"RYAAY": {
"p": 63.9,
"d": -1.13
},
"VOO": {
"p": 688.83,
"d": -0.72
},
"CRM": {
"p": 170.555,
"d": 4.43
},
"IOT": {
"p": 37.25,
"d": 1.44
},
"SMTI": {
"p": 24.66,
"d": 3.53
},
"SAP": {
"p": 160.175,
"d": 1.47
},
"SES": {
"p": 0.7039,
"d": -8.64
},
"SMH": {
"p": 586.21,
"d": -4.06
},
"NOW": {
"p": 111.275,
"d": 3.31
},
"SHOP": {
"p": 125.27,
"d": 2.23
},
"SNOW": {
"p": 269.663,
"d": 3.14
},
"SBUX": {
"p": 107.93,
"d": 1.81
},
"STNE": {
"p": 11.15,
"d": -0.54
},
"SG": {
"p": 8.27,
"d": -1.08
},
"TROW": {
"p": 113.22,
"d": -4.5
},
"TSM": {
"p": 423.62,
"d": -2.42
},
"TPR": {
"p": 136.1,
"d": -3.29
},
"TGT": {
"p": 135.475,
"d": 0.25
},
"TDOC": {
"p": 9.525,
"d": 2.64
},
"TCEHY": {
"p": 58.17,
"d": -1.91
},
"TSLA": {
"p": 392.78,
"d": -3.67
},
"HEAL": {
"p": 28.481,
"d": 0.46
},
"TTD": {
"p": 20.075,
"d": 2.79
},
"PATH": {
"p": 11.856,
"d": 1.51
},
"ULTA": {
"p": 473.13,
"d": 0.84
},
"UA": {
"p": 6.655,
"d": 0.68
},
"UNH": {
"p": 429.42,
"d": 1.13
},
"GDX": {
"p": 73.1,
"d": -3.22
},
"QNTM": {
"p": 3.48,
"d": 5.14
},
"VEEV": {
"p": 197.4,
"d": 3.83
},
"V": {
"p": 357.925,
"d": 2.57
},
"VST": {
"p": 157.32,
"d": -0.97
},
"WBD": {
"p": 27.265,
"d": 2.54
},
"WM": {
"p": 236.86,
"d": 1.51
},
"XOVR": {
"p": 20.27,
"d": -2.74
},
"ZM": {
"p": 91.919,
"d": 2.41
},
"IFX": {
"p": 70.37,
"d": -2.91
},
"SAN": {
"p": 77.1,
"d": 1.14
},
"ALV": {
"p": 421.0,
"d": -0.14
},
"HDB": {
"p": 26.45,
"d": -0.23
},
"SU": {
"p": 268.55,
"d": -0.41
},
"RHM": {
"p": 979.2,
"d": -1.29
},
"AEM": {
"p": 142.47,
"d": -3.0
},
"8058.T": {
"p": 4440.0,
"d": 0.7
},
"AZN": {
"p": 169.45,
"d": -1.26
},
"CCJ": {
"p": 89.86,
"d": -6.39
},
"AXA": {
"p": 44.32,
"d": 0.11
},
"TLX": {
"p": 112.4,
"d": 1.54
},
"MRK.DE": {
"p": 139.85,
"d": 0.11
},
"RDY": {
"p": 12.995,
"d": -1.48
},
"BAP": {
"p": 389.825,
"d": -2.74
},
"EURUSD": {
"p": 1.1391,
"d": -0.25
},
"EURJPY": {
"p": 184.891,
"d": 0.18
},
"EURCAD": {
"p": 1.6112,
"d": -0.24
},
"EURGBP": {
"p": 0.8523,
"d": 0.07
},
"EURCHF": {
"p": 0.927,
"d": 0.5
},
"EURSEK": {
"p": 11.053,
"d": 0.23
},
"APLD": {
"p": 28.79,
"d": -7.58
},
"IREN": {
"p": 38.97,
"d": -5.27
},
"MRVL": {
"p": 217.49,
"d": -7.77
},
"MU": {
"p": 931.075,
"d": -4.92
},
"SOFI": {
"p": 18.18,
"d": -3.19
},
"STM": {
"p": 68.57,
"d": -4.04
},
"REC": {
"p": 51.4,
"d": 0.19
},
"MUV2": {
"p": 510.0,
"d": 1.27
},
"IBN": {
"p": 29.272,
"d": 0.94
},
"IBE": {
"p": 21.14,
"d": 1.15
},
"GEV": {
"p": 1041.71,
"d": -4.57
},
"_updated": "2026-07-13 19:02:33 UTC"
}